super_scad_regular_polygon/Finished/D2/FinishedRegularPolygon.py
super_scad_regular_polygon/Finished/D2/FinishedRegularPolygonFinish.py
super_scad_regular_polygon/Finished/D2/FinishedRegularPolygonFinishChamfer.py
super_scad_regular_polygon/Finished/D2/FinishedRegularPolygonFinishFillet.py
super_scad_regular_polygon/Finished/D2/FinishedRegularPolygonFinishLollipop.py
super_scad_regular_polygon/Finished/D2/FinishedRegularPolygonFinishNone.py
super_scad_regular_polygon/Finished/D2/RoundedSquare.py
super_scad_regular_polygon/Finished/D2/__init__.py
super_scad_regular_polygon/Finished/__init__.py
super_scad_regular_polygon/__init__.py
super_scad_regular_polygon/d0/RegularPolygon.py
super_scad_regular_polygon-0.1.0.dist-info/LICENSE
super_scad_regular_polygon-0.1.0.dist-info/METADATA
super_scad_regular_polygon-0.1.0.dist-info/WHEEL
super_scad_regular_polygon-0.1.0.dist-info/RECORD
