Metadata-Version: 2.1
Name: Super-SCAD-Regular-Polygon
Version: 0.1.0
Summary: SuperSCAD widgets for regular polygons.
Home-page: https://github.com/SuperSCAD/SuperSCAD
License: MIT
Keywords: OpenSCAD,SuperSCAD,Regular Polygon
Author: P.R. Water
Author-email: p.r.water@setbased.nl
Requires-Python: >=3.10.0,<4.0.0
Classifier: Development Status :: 5 - Production/Stable
Classifier: Intended Audience :: Developers
Classifier: Intended Audience :: Manufacturing
Classifier: License :: OSI Approved :: MIT License
Classifier: Programming Language :: Python :: 3
Classifier: Programming Language :: Python :: 3.10
Classifier: Programming Language :: Python :: 3.11
Classifier: Programming Language :: Python :: 3.12
Classifier: Topic :: Multimedia :: Graphics :: 3D Modeling
Classifier: Topic :: Software Development :: Code Generators
Requires-Dist: super-scad (>=0.4.0,<0.5.0)
Project-URL: Documentation, https://superscad.readthedocs.io/
Project-URL: Repository, https://github.com/SuperSCAD/SuperSCAD
